github_http_api/__init__.py
github_http_api-0.2.5.dist-info/LICENSE
github_http_api-0.2.5.dist-info/METADATA
github_http_api-0.2.5.dist-info/WHEEL
github_http_api-0.2.5.dist-info/top_level.txt
github_http_api-0.2.5.dist-info/RECORD
