Metadata-Version: 2.1
Name: github-http-api
Version: 0.2.5
Summary: A simple github HTTP api handler in python.
Home-page: https://github.com/ThaaoBlues/github_api
Author: _ThaaoBlues_
Author-email: thaaoblues81@gmail.com
License: CC BY-NC-ND 4.0
Platform: UNKNOWN
Classifier: License :: Other/Proprietary License
Classifier: Programming Language :: Python
Classifier: Programming Language :: Python :: 3
Classifier: Programming Language :: Python :: 3.9
Requires-Python: >=3.6.0
License-File: LICENSE
Requires-Dist: requests
